reviser/__init__.py
reviser/bundling/__init__.py
reviser/bundling/_installer.py
reviser/cli.py
reviser/commands/__init__.py
reviser/commands/aliaser.py
reviser/commands/bundler.py
reviser/commands/configer.py
reviser/commands/deployer.py
reviser/commands/exiter.py
reviser/commands/helper/__init__.py
reviser/commands/helper/help.jinja2
reviser/commands/invoker.py
reviser/commands/lister.py
reviser/commands/pruner.py
reviser/commands/pusher.py
reviser/commands/region_switcher.py
reviser/commands/reloader.py
reviser/commands/reporter.py
reviser/commands/selector.py
reviser/commands/sheller.py
reviser/commands/tailer.py
reviser/definitions/__init__.py
reviser/definitions/abstracts.py
reviser/definitions/aws.py
reviser/definitions/configurations/__init__.py
reviser/definitions/configurations/bundling.py
reviser/definitions/configurations/depending.py
reviser/definitions/configurations/enviromentals.py
reviser/definitions/configurations/imaging.py
reviser/definitions/configurations/layering.py
reviser/definitions/configurations/targeting.py
reviser/definitions/contexts.py
reviser/definitions/enumerations.py
reviser/definitions/infomatics.py
reviser/definitions/selections.py
reviser/deploying/__init__.py
reviser/deploying/publisher.py
reviser/deploying/updater.py
reviser/deploying/uploader.py
reviser/interactivity/__init__.py
reviser/interactivity/completions.py
reviser/interactivity/runner.py
reviser/interactivity/shells/__init__.py
reviser/interactivity/shells/execution_result.jinja2
reviser/interactivity/shells/prompt.jinja2
reviser/interactivity/shells/splash.jinja2
reviser/parsing.py
reviser/servicer/__init__.py
reviser/servicer/functioning/__init__.py
reviser/servicer/functioning/echo_versions.jinja2
reviser/servicer/layering.py
reviser/templating/__init__.py
reviser/templating/error.jinja2
reviser/utils.py
reviser-0.4.11.dist-info/METADATA
reviser-0.4.11.dist-info/WHEEL
reviser-0.4.11.dist-info/entry_points.txt
reviser-0.4.11.dist-info/licenses/LICENSE
reviser-0.4.11.dist-info/RECORD
