Metadata-Version: 2.4
Name: reviser
Version: 0.4.11
Summary: AWS Lambda function/layer version deployment manager.
License: MIT
License-File: LICENSE
Keywords: aws,lambda
Author: Scott Ernst
Author-email: swernst@gmail.com
Requires-Python: >=3.11,<3.15
Classifier: Development Status :: 4 - Beta
Classifier: Environment :: Console
Classifier: Intended Audience :: Developers
Classifier: License :: OSI Approved :: MIT License
Classifier: Programming Language :: Python :: 3
Classifier: Programming Language :: Python :: 3.11
Classifier: Programming Language :: Python :: 3.12
Classifier: Programming Language :: Python :: 3.13
Classifier: Programming Language :: Python :: 3.14
Classifier: Topic :: Utilities
Classifier: Typing :: Typed
Provides-Extra: shell
Requires-Dist: Jinja2 (>=2.11.2) ; extra == "shell"
Requires-Dist: PyYAML (>=5.3.0) ; extra == "shell"
Requires-Dist: boto3 (>=1.35.88) ; extra == "shell"
Requires-Dist: colorama (>=0.4.4) ; extra == "shell"
Requires-Dist: pipper (>=0.10.0) ; extra == "shell"
Requires-Dist: prompt-toolkit (>=3.0.8) ; extra == "shell"
Requires-Dist: toml (>=0.10.0) ; extra == "shell"
Requires-Dist: wheel (>=0.37.1) ; extra == "shell"
Project-URL: Documentation, https://github.com/rocketboosters/reviser
Project-URL: Homepage, https://github.com/rocketboosters/reviser
Project-URL: Repository, https://github.com/rocketboosters/reviser
